django_pg_search-0.1.1.dist-info/DESCRIPTION.rst
django_pg_search-0.1.1.dist-info/METADATA
django_pg_search-0.1.1.dist-info/RECORD
django_pg_search-0.1.1.dist-info/WHEEL
django_pg_search-0.1.1.dist-info/metadata.json
django_pg_search-0.1.1.dist-info/top_level.txt
pgsearch/__init__.py
pgsearch/fields.py
pgsearch/lookups.py
pgsearch/managers.py
pgsearch/query.py
