Metadata-Version: 2.0
Name: django-pg-search
Version: 0.1.1
Summary: Django app for making PostgreSQL full text search queries
Home-page: https://github.com/akszydelko/django-pg-search
Author: Arkadiusz Szydelko
Author-email: akszydelko@gmail.com
License: BSD
Keywords: django postgresql full text search
Platform: UNKNOWN
Classifier: Development Status :: 4 - Beta
Classifier: Intended Audience :: Developers
Classifier: License :: OSI Approved :: BSD License
Classifier: Environment :: Web Environment
Classifier: Operating System :: OS Independent
Classifier: Programming Language :: Python
Classifier: Programming Language :: Python :: 2
Classifier: Programming Language :: Python :: 2.7
Classifier: Programming Language :: Python :: 3
Classifier: Programming Language :: Python :: 3.5
Classifier: Programming Language :: Python :: 3.6
Classifier: Framework :: Django
Requires-Dist: django (>=1.8)
Requires-Dist: psycopg2 (>=2.6.1)
